cognihub_pygotemplate-0.0.1.data/purelib/cognihub_pygotemplate/__init__.py
cognihub_pygotemplate-0.0.1.data/purelib/cognihub_pygotemplate/engine.py
cognihub_pygotemplate-0.0.1.data/purelib/cognihub_pygotemplate/librenderer.dylib
cognihub_pygotemplate-0.0.1.dist-info/LICENSE
cognihub_pygotemplate-0.0.1.dist-info/LICENSE copy
cognihub_pygotemplate-0.0.1.dist-info/METADATA
cognihub_pygotemplate-0.0.1.dist-info/WHEEL
cognihub_pygotemplate-0.0.1.dist-info/top_level.txt
cognihub_pygotemplate-0.0.1.dist-info/RECORD
