Metadata-Version: 2.1
Name: cognihub-pygotemplate
Version: 0.0.1
Summary: A Python wrapper for Go's text/template engine via CGo
Author-email: hsz <hsz1273327@gmail.com>
Classifier: Programming Language :: Python :: 3
Classifier: License :: OSI Approved :: MIT License
Classifier: Operating System :: OS Independent
Requires-Python: >=3.10
License-File: LICENSE
License-File: LICENSE copy
